codrone_simulator/__init__.py
codrone_simulator/codrone_simulator.py
codrone_simulator-0.2.7.dist-info/METADATA
codrone_simulator-0.2.7.dist-info/WHEEL
codrone_simulator-0.2.7.dist-info/top_level.txt
codrone_simulator-0.2.7.dist-info/RECORD
