Metadata-Version: 2.1
Name: codrone-simulator
Version: 0.2.7
Summary: A Python package for simulating drone operations and learning drone programming in a virtual environment.
Home-page: UNKNOWN
Author: 10boticsDev
Author-email: mark.protusada@10botics.com
License: CC-BY-ND-4.0
Project-URL: GitHub Repository, https://github.com/10botics/codrone-simulator-sdk-python
Project-URL: Drone Simulator Github, https://github.com/10botics/codrone-simulator
Platform: UNKNOWN
Classifier: Programming Language :: Python :: 3
Classifier: License :: Other/Proprietary License
Classifier: Operating System :: OS Independent
Requires-Python: >=3.6
